leticialair/__init__.py
leticialair/s3_actions.py
leticialair/s3_files.py
leticialair-0.0.1.dist-info/METADATA
leticialair-0.0.1.dist-info/WHEEL
leticialair-0.0.1.dist-info/top_level.txt
leticialair-0.0.1.dist-info/RECORD
